dagmate/__init__.py
dagmate/core.py
dagmate/utils.py
dagmate-0.2.0.dist-info/WHEEL
dagmate-0.2.0.dist-info/METADATA
dagmate-0.2.0.dist-info/RECORD
