Metadata-Version: 2.1
Name: dagmate
Version: 0.2.0
Summary: Make your Dagster deployment faster and easier with Dagmate
Author: Anoop Sharma
Requires-Python: >=3.7,<4.0
Classifier: Programming Language :: Python :: 3
Classifier: Programming Language :: Python :: 3.10
Classifier: Programming Language :: Python :: 3.7
Classifier: Programming Language :: Python :: 3.8
Classifier: Programming Language :: Python :: 3.9
Requires-Dist: dagit (>=0.14.13,<0.15.0)
Requires-Dist: dagster (>=0.14.13,<0.15.0)
Requires-Dist: dagster-graphql (>=0.14.13,<0.15.0)
Requires-Dist: protobuf (>=3.20.1,<3.21.0)
